[
	{
		"name": "domePixels",
		"rings": [
			{"offset":1,"px":[	[0,128],	[0,130],	[0,132],	[0,134],	[0,136],	[0,138],	[0,140],	[0,142],	[0,144],	[0,146],	[0,148],	[0,150]	]},
			{"px":[	[0,0],	[0,1],	[0,2],	[0,3],	[0,4],	[0,5],	[0,6],	[0,7],	[0,8],	[0,9],	[0,10],	[0,11]	]},
			{"px":[	[0,12],	[0,13],	[0,14],	[0,15],	[0,16],	[0,17],	[0,18],	[0,19],	[0,20],	[0,21],	[0,22],	[0,23]	]},
			{"px":[	[0,24],	[0,25],	[0,26],	[0,27],	[0,28],	[0,29],	[0,30],	[0,31],	[0,32],	[0,33],	[0,34],	[0,35]	]},
			{"px":[	[0,36],	[0,37],	[0,38],	[0,39],	[0,40],	[0,41],	[0,42],	[0,43],	[0,44],	[0,45],	[0,46],	[0,47]	]},
			{"px":[	[0,48],	[0,49],	[0,50],	[0,51],	[0,52],	[0,53],	[0,54],	[0,55],	[0,56],	[0,57],	[0,58],	[0,59]	]},
			{"offset":10,"px":[	[0,64,true],	[0,65,true],	[0,66,true],	[0,67,true],	[0,68,true],	[0,69,true],	[0,70,true],	[0,71,true],	[0,72,true],	[0,73,true],	[0,74,true],	[0,75,true]	]}
		],
		"strips": [
			{"px": [	[0,130],	[0,0],	[0,12],	[0,24],	[0,36],	[0,48],	[0,74,true]	]},
			{"px": [	[0,132],	[0,1],	[0,13],	[0,25],	[0,37],	[0,49],	[0,75,true]	]},
			{"px": [	[0,134],	[0,2],	[0,14],	[0,26],	[0,38],	[0,50],	[0,64,true]	]},
			{"px": [	[0,136],	[0,3],	[0,15],	[0,27],	[0,39],	[0,51],	[0,65,true]	]},
			{"px": [	[0,138],	[0,4],	[0,16],	[0,28],	[0,40],	[0,52],	[0,66,true]	]},
			{"px": [	[0,140],	[0,5],	[0,17],	[0,29],	[0,41],	[0,53],	[0,67,true]	]},
			{"px": [	[0,142],	[0,6],	[0,18],	[0,30],	[0,42],	[0,54],	[0,68,true]	]},
			{"px": [	[0,144],	[0,7],	[0,19],	[0,31],	[0,43],	[0,55],	[0,69,true]	]},
			{"px": [	[0,146],	[0,8],	[0,20],	[0,32],	[0,44],	[0,56],	[0,70,true]	]},
			{"px": [	[0,148],	[0,9],	[0,21],	[0,33],	[0,45],	[0,57],	[0,71,true]	]},
			{"px": [	[0,150],	[0,10],	[0,22],	[0,34],	[0,46],	[0,58],	[0,72,true]	]},
			{"px": [	[0,128],	[0,11],	[0,23],	[0,35],	[0,47],	[0,59],	[0,73,true]	]}
		]
	},
	{
		"name": "touch",
		"rings": [
			{"offset":1,"px":[	[0,128],	[0,130],	[0,132],	[0,134],	[0,136],	[0,138],	[0,140],	[0,142],	[0,144],	[0,146],	[0,148],	[0,150]	]}
		],
		"strips": [
			{"px": [	[0,130]	]},
			{"px": [	[0,132]	]},
			{"px": [	[0,134]	]},
			{"px": [	[0,136]	]},
			{"px": [	[0,138]	]},
			{"px": [	[0,140]	]},
			{"px": [	[0,142]	]},
			{"px": [	[0,144]	]},
			{"px": [	[0,146]	]},
			{"px": [	[0,148]	]},
			{"px": [	[0,150]	]},
			{"px": [	[0,128]	]}
		]
	},
	{
		"name": "inside",
		"rings": [
			{"offset":1,"px":[	[0,129],	[0,131],	[0,133],	[0,135],	[0,137],	[0,139],	[0,141],	[0,143],	[0,145],	[0,147],	[0,149],	[0,151]	]}
		],
		"strips": [
			{"px": [	[0,129]	]},
			{"px": [	[0,131]	]},
			{"px": [	[0,133]	]},
			{"px": [	[0,135]	]},
			{"px": [	[0,137]	]},
			{"px": [	[0,139]	]},
			{"px": [	[0,141]	]},
			{"px": [	[0,143]	]},
			{"px": [	[0,145]	]},
			{"px": [	[0,147]	]},
			{"px": [	[0,149]	]},
			{"px": [	[0,151]	]}
		]
	},
	{
		"name": "player2",
		"rings": [
			{"px": [	[0,192],	[0,193],	[0,194],	[0,195],	[0,196],	[0,197],	[0,198],	[0,199]	]}
		],
		"strips": [
			{"px": [[0,192]]},
			{"px": [[0,193]]},
			{"px": [[0,194]]},
			{"px": [[0,195]]},
			{"px": [[0,196]]},
			{"px": [[0,197]]},
			{"px": [[0,198]]},
			{"px": [[0,199]]}
		]
	},
	{
		"name": "player1",
		"rings": [
			{"px": [	[0,256],	[0,257],	[0,258],	[0,259],	[0,260],	[0,261],	[0,262],	[0,263]	]}
		],
		"strips": [
			{"px": [[0,256]]},	
			{"px": [[0,257]]},	
			{"px": [[0,258]]},	
			{"px": [[0,259]]},	
			{"px": [[0,260]]},	
			{"px": [[0,261]]},	
			{"px": [[0,262]]},	
			{"px": [[0,263]]}
		]
	}
]